re_helper/__init__.py
re_helper/re_help.py
re_helper-1.2.4.dist-info/METADATA
re_helper-1.2.4.dist-info/WHEEL
re_helper-1.2.4.dist-info/top_level.txt
re_helper-1.2.4.dist-info/RECORD
