Metadata-Version: 2.1
Name: re-helper
Version: 1.2.4
Summary: re tool easy for use
Home-page: https://github.com/abo123456789/re_helper
Author: cc
Author-email: abcdef123456chen@sohu.com
Maintainer: cc
Maintainer-email: abcdef123456chen@sohu.com
License: MIT License
Keywords: re_helper
Platform: all
Classifier: Development Status :: 4 - Beta
Classifier: Operating System :: OS Independent
Classifier: Intended Audience :: Developers
Classifier: License :: OSI Approved :: MIT License
Classifier: Programming Language :: Python
Classifier: Programming Language :: Python :: Implementation
Classifier: Programming Language :: Python :: 3.6
Classifier: Programming Language :: Python :: 3.7
Classifier: Programming Language :: Python :: 3.8
Classifier: Programming Language :: Python :: 3.9
Classifier: Programming Language :: Python :: 3.10
Classifier: Topic :: Software Development :: Libraries
